ClientShowBusinessTg/ClientShowBusinessTg.py
ClientShowBusinessTg/__init__.py
ClientShowBusinessTg-0.1.dist-info/METADATA
ClientShowBusinessTg-0.1.dist-info/WHEEL
ClientShowBusinessTg-0.1.dist-info/top_level.txt
ClientShowBusinessTg-0.1.dist-info/RECORD
