Metadata-Version: 2.1
Name: ClientShowBusinessTg
Version: 0.1
Summary: async upload archive
Author: showbusiness
Author-email: fefrwerfre53@tutamail.com
Classifier: Programming Language :: Python :: 3
Classifier: License :: OSI Approved :: MIT License
Classifier: Operating System :: OS Independent
Requires-Python: >=3.11
